LICENSE.txt
MANIFEST.in
README.md
pydmtools.c
pydmtools.h
setup.cfg
setup.py
libdm/.DS_Store
libdm/README.md
libdm/binaMeth.h
libdm/binaMethIO.h
libdm/bmCommon.h
libdm/bmRead.c
libdm/bmStats.c
libdm/bmValues.c
libdm/bmValues.h
libdm/bmWrite.c
libdm/io.c
libdm/regression.cpp
libdm/regression.hpp
libdm/update_from_dmtools.sh
pydmtest/__init__.py
pydmtest/test.dm
pydmtest/test.py
pydmtest/testnp.dm
pydmtools/__init__.py
pydmtools/highlevel.py
tests/test_context_manager.py
tests/test_entries.py
tests/test_highlevel.py