Metadata-Version: 2.4
Name: pydmtools
Version: 0.1.6
Summary: A Software Package for Accessing and Manipulating DM Files
Home-page: https://github.com/ZhouQiangwei/pydmtools.git
Download-URL: 
Author: momocoding
Author-email: 
Keywords: bioinformatics,DNA methylation,DM,dmtools
Classifier: Development Status :: 5 - Production/Stable
Classifier: Intended Audience :: Developers
Classifier: License :: OSI Approved
Classifier: Programming Language :: C
Classifier: Programming Language :: Python
Classifier: Programming Language :: Python :: 3
Classifier: Programming Language :: Python :: 3.8
Classifier: Programming Language :: Python :: 3.9
Classifier: Programming Language :: Python :: 3.10
Classifier: Programming Language :: Python :: 3.11
Classifier: Programming Language :: Python :: 3.12
Classifier: Programming Language :: Python :: Implementation :: CPython
Classifier: Operating System :: POSIX
Classifier: Operating System :: Unix
Classifier: Operating System :: MacOS
Requires-Python: >=3.8
License-File: LICENSE.txt
Provides-Extra: numpy-input
Requires-Dist: numpy; extra == "numpy-input"
Dynamic: author
Dynamic: classifier
Dynamic: home-page
Dynamic: keywords
Dynamic: license-file
Dynamic: provides-extra
Dynamic: requires-python
Dynamic: summary
